CHANGELOG.md
kielmat/__init__.py
kielmat/config.py
kielmat/datasets/__init__.py
kielmat/datasets/fairpark.py
kielmat/datasets/keepcontrol.py
kielmat/datasets/mobilised.py
kielmat/modules/__init__.py
kielmat/modules/gsd/__init__.py
kielmat/modules/gsd/_paraschiv.py
kielmat/modules/icd/__init__.py
kielmat/modules/icd/_paraschiv.py
kielmat/modules/pam/__init__.py
kielmat/modules/pam/_pam.py
kielmat/modules/ssd/__init__.py
kielmat/modules/ssd/_pham.py
kielmat/test/example_lower_back_acc.csv
kielmat/test/scripts/test.py
kielmat/test/test_calc.py
kielmat/test/test_datasets.py
kielmat/test/test_modules.py
kielmat/test/test_utils.py
kielmat/utils/file_io.py
kielmat/utils/FIR_2_3Hz_40.mat
kielmat/utils/importers.py
kielmat/utils/kielmat_dataclass.py
kielmat/utils/matlab_loader.py
kielmat/utils/orientation_estimation/__init__.py
kielmat/utils/orientation_estimation/_madgwick.py
kielmat/utils/preprocessing.py
kielmat/utils/quaternion.py
kielmat-0.0.5.dist-info/LICENSE
kielmat-0.0.5.dist-info/METADATA
kielmat-0.0.5.dist-info/WHEEL
kielmat-0.0.5.dist-info/RECORD
