Metadata-Version: 2.1
Name: kielmat
Version: 0.0.5
Summary: The KielMotionAnalysisToolbox (KielMAT) is a Python-based toolbox for processing motion data.
Home-page: https://neurogeriatricskiel.github.io/KielMAT/
License: MIT
Author: Masoud Abedinifar
Author-email: Masoud.Abedinifar@uksh.de
Maintainer: Masoud Abedinifar
Maintainer-email: Masoud.Abedinifar@uksh.de
Requires-Python: >=3.10.0,<3.13
Classifier: License :: OSI Approved :: MIT License
Classifier: Programming Language :: Python :: 3
Classifier: Programming Language :: Python :: 3.10
Classifier: Programming Language :: Python :: 3.11
Provides-Extra: docs
Requires-Dist: actipy (>=3.0.5,<4.0.0)
Requires-Dist: bids-validator (>=1.14.4,<2.0.0)
Requires-Dist: h5py (>=3.10.0,<4.0.0)
Requires-Dist: ipykernel (>=6.26.0,<7.0.0)
Requires-Dist: json-repair (>=0.8.0,<0.9.0)
Requires-Dist: matplotlib (>=3.8.1,<4.0.0)
Requires-Dist: numpy (>=1.25)
Requires-Dist: openneuro-py (>=2024.2.0,<2025.0.0)
Requires-Dist: pandas (>=2)
Requires-Dist: polars (>=0.20.5,<0.21.0)
Requires-Dist: pooch (>=1.8.2,<2.0.0)
Requires-Dist: pyarrow (>=15.0.0,<16.0.0)
Requires-Dist: pytest (>=7.4.3,<8.0.0)
Requires-Dist: pywavelets (>=1.4.1,<2.0.0)
Requires-Dist: qmt (>=0.2.4,<0.3.0)
Requires-Dist: scipy (>=1.11.0)
Requires-Dist: seaborn (>=0.13.1,<0.14.0)
Requires-Dist: tpcp (>=0.27.0,<0.28.0)
Requires-Dist: vqf (>=2.0.0,<3.0.0)
Project-URL: Documentation, https://neurogeriatricskiel.github.io/KielMAT
Project-URL: Repository, https://github.com/neurogeriatricskiel/KielMAT
